beancount_tb_plugins/__init__.py
beancount_tb_plugins/auto_ratios/README.md
beancount_tb_plugins/auto_ratios/__init__.py
beancount_tb_plugins/auto_ratios/auto_ratios.py
beancount_tb_plugins/noduplicates_extended/README.md
beancount_tb_plugins/noduplicates_extended/__init__.py
beancount_tb_plugins/noduplicates_extended/commodity_attr.py
beancount_tb_plugins/noduplicates_extended/commodity_attr_test.py
beancount_tb_plugins/noduplicates_extended/noduplicates.beancount
beancount_tb_plugins/noduplicates_extended/noduplicates_extended.py
beancount_tb_plugins/noduplicates_extended/noduplicates_test.py
beancount_tb_plugins-0.1.4.dist-info/METADATA
beancount_tb_plugins-0.1.4.dist-info/WHEEL
beancount_tb_plugins-0.1.4.dist-info/licenses/LICENSE
beancount_tb_plugins-0.1.4.dist-info/RECORD
