Metadata-Version: 2.4
Name: beancount_tb_plugins
Version: 0.1.4
Summary: A.set of plugins for the Beancount plaintext accounting system
Project-URL: Homepage, https://github.com/tatablack/tatabeans
Project-URL: Issues, https://github.com/tatablack/tatabeans/issues
Author-email: Angelo Tata <beancount.projects@tatablack.net>
License-Expression: MIT
License-File: LICENSE
Classifier: Development Status :: 3 - Alpha
Classifier: Intended Audience :: Financial and Insurance Industry
Classifier: License :: OSI Approved :: MIT License
Classifier: Natural Language :: English
Classifier: Operating System :: OS Independent
Classifier: Programming Language :: Python :: 3 :: Only
Classifier: Programming Language :: Python :: 3.10
Classifier: Topic :: Office/Business :: Financial :: Accounting
Classifier: Topic :: Office/Business :: Financial :: Investment
Requires-Python: >=3.10
Requires-Dist: beancount>=3.1.0
Requires-Dist: xxhash>=3.5.0
